github_repo_bulk_deleter/__init__.py
github_repo_bulk_deleter/cli.py
github_repo_bulk_deleter/core.py
github_repo_bulk_delete-0.1.2.dist-info/METADATA
github_repo_bulk_delete-0.1.2.dist-info/WHEEL
github_repo_bulk_delete-0.1.2.dist-info/entry_points.txt
github_repo_bulk_delete-0.1.2.dist-info/top_level.txt
github_repo_bulk_delete-0.1.2.dist-info/RECORD
