Metadata-Version: 2.2
Name: github-repo-bulk-delete
Version: 0.1.2
Summary: A CLI tool to interactively select and delete multiple GitHub repositories
Home-page: https://github.com/conficiusa/github-repo-bulk-delete
Author: conficiusa
Author-email: your.email@example.com
Classifier: Programming Language :: Python :: 3
Classifier: License :: OSI Approved :: MIT License
Classifier: Operating System :: OS Independent
Requires-Python: >=3.6
Requires-Dist: requests
Requires-Dist: blessed
Dynamic: author
Dynamic: author-email
Dynamic: classifier
Dynamic: description
Dynamic: description-content-type
Dynamic: home-page
Dynamic: requires-dist
Dynamic: requires-python
Dynamic: summary
